Metadata-Version: 2.1
Name: ja2sci
Version: 0.1.3
Summary: Translate Japanese name into scientific name
Home-page: https://github.com/AzukiOtter/ja2sci
Author: AzukiOtter
Author-email: ogran.std@gmail.com
License: MIT
Keywords: biology species
Platform: UNKNOWN
Classifier: Development Status :: 4 - Beta
Classifier: Intended Audience :: Developers
Classifier: Programming Language :: Python :: 3.6
Classifier: Programming Language :: Python :: 3.7
Requires-Python: >=3.6, <4
